pepflow/__init__.py
pepflow/constants.py
pepflow/constraint.py
pepflow/constraint_test.py
pepflow/dual_interactive_constraint.py
pepflow/e2e_test.py
pepflow/expression_manager.py
pepflow/expression_manager_test.py
pepflow/function.py
pepflow/function_test.py
pepflow/ipython_utils.py
pepflow/logging.py
pepflow/math_expression.py
pepflow/operator.py
pepflow/operator_test.py
pepflow/parameter.py
pepflow/parameter_test.py
pepflow/pep.py
pepflow/pep_context.py
pepflow/pep_context_test.py
pepflow/pep_result.py
pepflow/pep_test.py
pepflow/plot_data.py
pepflow/primal_interactive_constraint.py
pepflow/registry.py
pepflow/scalar.py
pepflow/scalar_test.py
pepflow/solver.py
pepflow/solver_test.py
pepflow/utils.py
pepflow/vector.py
pepflow/vector_test.py
pepflow-0.1.8.dist-info/licenses/LICENSE
pepflow-0.1.8.dist-info/METADATA
pepflow-0.1.8.dist-info/WHEEL
pepflow-0.1.8.dist-info/top_level.txt
pepflow-0.1.8.dist-info/RECORD
