Metadata-Version: 2.4
Name: pepflow
Version: 0.1.8
Summary: PEPFlow: A framework for Performance Estimation Problem (PEP) Workflow
Requires-Python: >=3.10
License-File: LICENSE
Requires-Dist: attrs>=25.3.0
Requires-Dist: cvxpy>=1.7.1
Requires-Dist: dash>=3.2.0
Requires-Dist: dash-bootstrap-components>=2.0.3
Requires-Dist: ipykernel>=7.1.0
Requires-Dist: isort>=6.0.1
Requires-Dist: matplotlib>=3.9.4
Requires-Dist: natsort>=8.4.0
Requires-Dist: numpy>=2.0.2
Requires-Dist: pandas>=2.3.1
Requires-Dist: plotly>=6.3.0
Requires-Dist: pytest>=8.4.1
Requires-Dist: ruff>=0.12.4
Requires-Dist: sympy>=1.14.0
Dynamic: license-file
